docker_inspector/__init__.py
docker_inspector/app.py
docker_inspector/styles/main.css
docker_inspector/utils/__init__.py
docker_inspector/utils/get_info.py
docker_inspector/widgets/__init__.py
docker_inspector/widgets/container_list.py
docker_inspector/widgets/volume_list.py
docker_inspector-0.1.13.dist-info/METADATA
docker_inspector-0.1.13.dist-info/WHEEL
docker_inspector-0.1.13.dist-info/entry_points.txt
docker_inspector-0.1.13.dist-info/RECORD
