Metadata-Version: 2.1
Name: docker-inspector
Version: 0.1.13
Summary: 
Author: antonio
Author-email: mr.antonsilin@gmail.com
Requires-Python: >=3.9,<4.0
Classifier: Programming Language :: Python :: 3
Classifier: Programming Language :: Python :: 3.9
Classifier: Programming Language :: Python :: 3.10
Classifier: Programming Language :: Python :: 3.11
Classifier: Programming Language :: Python :: 3.12
Requires-Dist: textual (>=0.56.3,<0.57.0)
